{
  "required": true,
  "minVersion": "0.8",
  "package": "com.leclowndu93150.sea_of_chests.mixin",
  "compatibilityLevel": "JAVA_8",
  "refmap": "sea_of_chests.refmap.json",
  "mixins": [
    "BaseContainerBlockEntityMixin",
    "ChestBlockMixin",
    "ChunkManagerMixin",
    "ChunkMixin",
    "ChunkUnloadMixin",
    "MixinLevelChunk",
    "carryon.PickupHandlerMixin",
    "carryon.PlacementHandlerAccessor",
    "carryon.PlacementHandlerMixin"
  ],
  "client": [
    "client.LevelRendererMixin"
  ],
  "injectors": {
    "defaultRequire": 1
  },
  "overwrites": {
    "requireAnnotations": true
  }
}
